{
  "city": "bingol",
  "cityDisplayName": "Bingöl",
  "updatedAt": "2026-04-21T05:40:15.975Z",
  "isStale": false,
  "pharmacies": [
    {
      "id": "fec671e0cf1af8a26733f3fd55d6ca14",
      "name": "GENÇ MURAT",
      "address": "CUMHURİYET MAH CUMHURİYET CAD NO 14/B GENÇ/BİNGÖL",
      "phoneNumber": "0 - (426) 411 - 3223",
      "district": "Genç",
      "latitude": 38.7524356,
      "longitude": 40.5638822,
      "dutyStart": null,
      "dutyEnd": null,
      "lastVerifiedAt": "2026-04-21T05:40:15.975Z",
      "source": "e-Devlet / TİTCK",
      "sourceUrl": "https://www.turkiye.gov.tr/saglik-titck-nobetci-eczane-sorgulama"
    },
    {
      "id": "4d68da3643832c20c6e559ed05741f7f",
      "name": "NADİROĞLU",
      "address": "Yeşilyurt Mahallesi Fatih Caddesi No:52/B",
      "phoneNumber": "0 - (426) 511 - 2595",
      "district": "Karlıova",
      "latitude": 39.2945998,
      "longitude": 41.0102383,
      "dutyStart": null,
      "dutyEnd": null,
      "lastVerifiedAt": "2026-04-21T05:40:15.975Z",
      "source": "e-Devlet / TİTCK",
      "sourceUrl": "https://www.turkiye.gov.tr/saglik-titck-nobetci-eczane-sorgulama"
    },
    {
      "id": "1d1998ccb517a9266d24e50e7a9be334",
      "name": "BARAN",
      "address": "İNÖNÜ MAH. GENÇ CAD. NO:40 MERKEZ/BİNGÖL",
      "phoneNumber": "0 - (426) 213 - 5052",
      "district": "Merkez",
      "latitude": 38.8848037,
      "longitude": 40.4976651,
      "dutyStart": null,
      "dutyEnd": null,
      "lastVerifiedAt": "2026-04-21T05:40:15.975Z",
      "source": "e-Devlet / TİTCK",
      "sourceUrl": "https://www.turkiye.gov.tr/saglik-titck-nobetci-eczane-sorgulama"
    },
    {
      "id": "1d0645461733abc1fcb6cf9160e95c33",
      "name": "YAŞAM",
      "address": "SARAY MAH.SAĞLIK CAD. NO:26/A",
      "phoneNumber": "0 - (426) 215 - 0723",
      "district": "Merkez",
      "latitude": 38.882027,
      "longitude": 40.4972698,
      "dutyStart": null,
      "dutyEnd": null,
      "lastVerifiedAt": "2026-04-21T05:40:15.975Z",
      "source": "e-Devlet / TİTCK",
      "sourceUrl": "https://www.turkiye.gov.tr/saglik-titck-nobetci-eczane-sorgulama"
    },
    {
      "id": "5c30b60bdd28e723a4265eb608dac65a",
      "name": "BARAN",
      "address": "Yeni mahalle 345. sokak sağlık sitesi No:6/A Solhan / Bingöl",
      "phoneNumber": "0 - (537) 453 - 6935",
      "district": "Solhan",
      "latitude": 38.9659351,
      "longitude": 41.0518147,
      "dutyStart": null,
      "dutyEnd": null,
      "lastVerifiedAt": "2026-04-21T05:40:15.975Z",
      "source": "e-Devlet / TİTCK",
      "sourceUrl": "https://www.turkiye.gov.tr/saglik-titck-nobetci-eczane-sorgulama"
    }
  ]
}
