{
  "city": "zonguldak",
  "cityDisplayName": "Zonguldak",
  "updatedAt": "2026-04-14T06:47:01.392Z",
  "isStale": false,
  "pharmacies": [
    {
      "id": "dfa755b7f85e0cd32ee33c161d5bacc5",
      "name": "ÖZTÜRK",
      "address": "MERKEZ MAH.HÜKÜMET CAD.NO:5/A",
      "phoneNumber": "0 - (372) 378 - 0881",
      "district": "Alaplı",
      "latitude": 41.180375,
      "longitude": 31.3861776,
      "dutyStart": null,
      "dutyEnd": null,
      "lastVerifiedAt": "2026-04-14T06:47:01.392Z",
      "source": "e-Devlet / TİTCK",
      "sourceUrl": "https://www.turkiye.gov.tr/saglik-titck-nobetci-eczane-sorgulama"
    },
    {
      "id": "170b16f1b01aca7fab8eb8d27c7b5001",
      "name": "DERMAN",
      "address": "ÇAY MAH.HASTANE SOK.ATATÜRK İŞ MERKEZİ NO:1/A",
      "phoneNumber": "0 - (372) 615 - 0090",
      "district": "Çaycuma",
      "latitude": 41.4269456,
      "longitude": 32.0728211,
      "dutyStart": null,
      "dutyEnd": null,
      "lastVerifiedAt": "2026-04-14T06:47:01.392Z",
      "source": "e-Devlet / TİTCK",
      "sourceUrl": "https://www.turkiye.gov.tr/saglik-titck-nobetci-eczane-sorgulama"
    },
    {
      "id": "d567695a713f30a35972c37818101172",
      "name": "HİSARÖNÜ",
      "address": "FİLYOS BELDESİ, ÖTEYÜZ MAH.İSMETPAŞA CAD.NO:23/C",
      "phoneNumber": "0 - (372) 623 - 1064",
      "district": "Çaycuma",
      "latitude": 41.4269456,
      "longitude": 32.0728211,
      "dutyStart": null,
      "dutyEnd": null,
      "lastVerifiedAt": "2026-04-14T06:47:01.392Z",
      "source": "e-Devlet / TİTCK",
      "sourceUrl": "https://www.turkiye.gov.tr/saglik-titck-nobetci-eczane-sorgulama"
    },
    {
      "id": "803b2e0afea505e71f1989be274502f6",
      "name": "TUBA",
      "address": "KARAPINAR BELDESİ, MERKEZ MAH.MİLLİ EGEMENLİK CAD.4/A",
      "phoneNumber": "0 - (372) 628 - 3330",
      "district": "Çaycuma",
      "latitude": 41.4269456,
      "longitude": 32.0728211,
      "dutyStart": null,
      "dutyEnd": null,
      "lastVerifiedAt": "2026-04-14T06:47:01.392Z",
      "source": "e-Devlet / TİTCK",
      "sourceUrl": "https://www.turkiye.gov.tr/saglik-titck-nobetci-eczane-sorgulama"
    },
    {
      "id": "738f23b579eebd5998db0efdd892370a",
      "name": "SERHAT",
      "address": "NEBİOĞLU BELDESİ, YENİPAZAR MAHALLESİ, CUMHURİYET CADDESİ NO:50/B",
      "phoneNumber": "0 - (372) 638 - 6030",
      "district": "Çaycuma",
      "latitude": 41.4269456,
      "longitude": 32.0728211,
      "dutyStart": null,
      "dutyEnd": null,
      "lastVerifiedAt": "2026-04-14T06:47:01.392Z",
      "source": "e-Devlet / TİTCK",
      "sourceUrl": "https://www.turkiye.gov.tr/saglik-titck-nobetci-eczane-sorgulama"
    },
    {
      "id": "ef96f8d2922a151f1b95b17b9e8538ff",
      "name": "BİRİNCİ",
      "address": "PERŞEMBE BELDESİ MERKEZ MAHALLESİ KÖKSAL TOPTAN BULVARI 7/A",
      "phoneNumber": "0 - (372) 638 - 6136",
      "district": "Çaycuma",
      "latitude": 41.4269456,
      "longitude": 32.0728211,
      "dutyStart": null,
      "dutyEnd": null,
      "lastVerifiedAt": "2026-04-14T06:47:01.392Z",
      "source": "e-Devlet / TİTCK",
      "sourceUrl": "https://www.turkiye.gov.tr/saglik-titck-nobetci-eczane-sorgulama"
    },
    {
      "id": "b1064093f3eeba905a7d31de8b1a06fb",
      "name": "SALTUKOVA",
      "address": "Saltukova Beldesi Kokaksu Mah. Hürriyet Caddesi No:124/B Çaycuma/Zonguldak",
      "phoneNumber": "3 - (726) 182 - 010_",
      "district": "Çaycuma",
      "latitude": 41.4269456,
      "longitude": 32.0728211,
      "dutyStart": null,
      "dutyEnd": null,
      "lastVerifiedAt": "2026-04-14T06:47:01.392Z",
      "source": "e-Devlet / TİTCK",
      "sourceUrl": "https://www.turkiye.gov.tr/saglik-titck-nobetci-eczane-sorgulama"
    },
    {
      "id": "cf147fde394b890c66571ab2a898715b",
      "name": "UMUT",
      "address": "YENİ MAH.VEDAT ALİ ÖZKAN CAD. NO:20",
      "phoneNumber": "0 - (372) 556 - 1014",
      "district": "Devrek",
      "latitude": 41.2188823,
      "longitude": 31.9558348,
      "dutyStart": null,
      "dutyEnd": null,
      "lastVerifiedAt": "2026-04-14T06:47:01.392Z",
      "source": "e-Devlet / TİTCK",
      "sourceUrl": "https://www.turkiye.gov.tr/saglik-titck-nobetci-eczane-sorgulama"
    },
    {
      "id": "f6133f537d217c169f035dad3063f17d",
      "name": "MERYEM",
      "address": "MÜFTÜ MAH.İBRAHİM EFE CAD.NO:55/B",
      "phoneNumber": "0 - (372) 323 - 8008",
      "district": "Ereğli",
      "latitude": 41.2722216,
      "longitude": 31.4341366,
      "dutyStart": null,
      "dutyEnd": null,
      "lastVerifiedAt": "2026-04-14T06:47:01.392Z",
      "source": "e-Devlet / TİTCK",
      "sourceUrl": "https://www.turkiye.gov.tr/saglik-titck-nobetci-eczane-sorgulama"
    },
    {
      "id": "91f6fdbe3a6a829db15abe1b3cb22cfe",
      "name": "GİZEM",
      "address": "SARIKORKMAZ MAH. ŞEHİT ER KUDRET ÖZCAN SOK. NO:5/C",
      "phoneNumber": "0 - (372) 322 - 0038",
      "district": "Ereğli",
      "latitude": 41.2839737,
      "longitude": 31.430429,
      "dutyStart": null,
      "dutyEnd": null,
      "lastVerifiedAt": "2026-04-14T06:47:01.392Z",
      "source": "e-Devlet / TİTCK",
      "sourceUrl": "https://www.turkiye.gov.tr/saglik-titck-nobetci-eczane-sorgulama"
    },
    {
      "id": "cc50d1e57b751eaa60b759897105ca4a",
      "name": "HAYAT",
      "address": "ORMANLI BELDESİ SİNİTLİ MAH.ATATÜRK CAD.NO:3/A",
      "phoneNumber": "0 - (372) 344 - 6054",
      "district": "Ereğli",
      "latitude": 41.2795516,
      "longitude": 31.4229672,
      "dutyStart": null,
      "dutyEnd": null,
      "lastVerifiedAt": "2026-04-14T06:47:01.392Z",
      "source": "e-Devlet / TİTCK",
      "sourceUrl": "https://www.turkiye.gov.tr/saglik-titck-nobetci-eczane-sorgulama"
    },
    {
      "id": "c050ffda450ee95dd1db3be7179ce083",
      "name": "BÜŞRA",
      "address": "Süleymanbeyler Köyü Hacullu Mahallesi No:3/3",
      "phoneNumber": "0 - (372) 323 - 0666",
      "district": "Ereğli",
      "latitude": 41.2795516,
      "longitude": 31.4229672,
      "dutyStart": null,
      "dutyEnd": null,
      "lastVerifiedAt": "2026-04-14T06:47:01.392Z",
      "source": "e-Devlet / TİTCK",
      "sourceUrl": "https://www.turkiye.gov.tr/saglik-titck-nobetci-eczane-sorgulama"
    },
    {
      "id": "5e5e30f42dd28a63d2a9ebb9a0f9410f",
      "name": "OKTAY",
      "address": "GÖKÇEBEY İLÇESİ İSTASYON MAH.ATATÜRK CAD.NO:48",
      "phoneNumber": "0 - (372) 512 - 3345",
      "district": "Gökçebey",
      "latitude": 41.3067487,
      "longitude": 32.1384667,
      "dutyStart": null,
      "dutyEnd": null,
      "lastVerifiedAt": "2026-04-14T06:47:01.392Z",
      "source": "e-Devlet / TİTCK",
      "sourceUrl": "https://www.turkiye.gov.tr/saglik-titck-nobetci-eczane-sorgulama"
    },
    {
      "id": "9b7a21c7a2588c3864811ceacd919959",
      "name": "EBRU",
      "address": "ÇATALAĞZI BELDESİ, MERKEZ MAHALLESİ, ATATÜRK CADDESİ, NO:28/A",
      "phoneNumber": "0 - (372) 264 - 1064",
      "district": "Kilimli",
      "latitude": 41.4841878,
      "longitude": 31.8581689,
      "dutyStart": null,
      "dutyEnd": null,
      "lastVerifiedAt": "2026-04-14T06:47:01.392Z",
      "source": "e-Devlet / TİTCK",
      "sourceUrl": "https://www.turkiye.gov.tr/saglik-titck-nobetci-eczane-sorgulama"
    },
    {
      "id": "b4e1e3b11e823ff5111f0b4b82e52e6d",
      "name": "DEFNE",
      "address": "MERKEZ MAHALLESİ, ATATÜRK CADDESİ, NO:44/11",
      "phoneNumber": "0 - (372) 201 - 0404",
      "district": "Kilimli",
      "latitude": 41.489143,
      "longitude": 31.8388774,
      "dutyStart": null,
      "dutyEnd": null,
      "lastVerifiedAt": "2026-04-14T06:47:01.392Z",
      "source": "e-Devlet / TİTCK",
      "sourceUrl": "https://www.turkiye.gov.tr/saglik-titck-nobetci-eczane-sorgulama"
    },
    {
      "id": "8329017d0407d81d9bf018fa32f55d41",
      "name": "BİLLUR",
      "address": "19 MAYIS MAH. ATATÜRK CADDESİ 5/B",
      "phoneNumber": "0 - (372) 269 - 0033",
      "district": "Kozlu",
      "latitude": 41.4338739,
      "longitude": 31.7472847,
      "dutyStart": null,
      "dutyEnd": null,
      "lastVerifiedAt": "2026-04-14T06:47:01.392Z",
      "source": "e-Devlet / TİTCK",
      "sourceUrl": "https://www.turkiye.gov.tr/saglik-titck-nobetci-eczane-sorgulama"
    },
    {
      "id": "f43a1c68b2b3de8a4878d4891496b10c",
      "name": "ÇAĞLAR",
      "address": "FATİH MAH. ŞEHİT GÖKHAN AVCI SOK.NO:2/A",
      "phoneNumber": "0 - (372) 265 - 6770",
      "district": "Kozlu",
      "latitude": 41.4318121,
      "longitude": 31.730838,
      "dutyStart": null,
      "dutyEnd": null,
      "lastVerifiedAt": "2026-04-14T06:47:01.392Z",
      "source": "e-Devlet / TİTCK",
      "sourceUrl": "https://www.turkiye.gov.tr/saglik-titck-nobetci-eczane-sorgulama"
    },
    {
      "id": "9cbebd29af407e1a2b8b5619a7fa72a6",
      "name": "BOZKURT",
      "address": "ESENKÖY MAHALLESİ, ABAZ CADDESİ, NO:198/3A",
      "phoneNumber": "0 - (372) 261 - 0061",
      "district": "Kozlu",
      "latitude": 41.4338739,
      "longitude": 31.7472847,
      "dutyStart": null,
      "dutyEnd": null,
      "lastVerifiedAt": "2026-04-14T06:47:01.392Z",
      "source": "e-Devlet / TİTCK",
      "sourceUrl": "https://www.turkiye.gov.tr/saglik-titck-nobetci-eczane-sorgulama"
    },
    {
      "id": "091ef8d29759b5b534dcbb6eec4ddcbc",
      "name": "MÜGE",
      "address": "MERKEZ İLÇE, İNCİVEZ MAH.ÜNİVERSİTE CAD.NO:19/L",
      "phoneNumber": "0 - (372) 257 - 2630",
      "district": "Merkez",
      "latitude": 41.4489894,
      "longitude": 31.7621279,
      "dutyStart": null,
      "dutyEnd": null,
      "lastVerifiedAt": "2026-04-14T06:47:01.392Z",
      "source": "e-Devlet / TİTCK",
      "sourceUrl": "https://www.turkiye.gov.tr/saglik-titck-nobetci-eczane-sorgulama"
    },
    {
      "id": "41edf2521874ada6baf9f5e18632f844",
      "name": "ALA",
      "address": "Terakki Mahallesi, Vatan Caddesi, No:7/C",
      "phoneNumber": "0 - (372) 250 - 0028",
      "district": "Merkez",
      "latitude": 41.4478151,
      "longitude": 31.7813029,
      "dutyStart": null,
      "dutyEnd": null,
      "lastVerifiedAt": "2026-04-14T06:47:01.392Z",
      "source": "e-Devlet / TİTCK",
      "sourceUrl": "https://www.turkiye.gov.tr/saglik-titck-nobetci-eczane-sorgulama"
    },
    {
      "id": "0f772f3e6b644f593ae8e9829f23e066",
      "name": "OKAY AYÇİÇEK",
      "address": "MERKEZ İLÇE, TEPEBAŞI MAH.YAPKENT SOK.143/1",
      "phoneNumber": "0 - (372) 268 - 3223",
      "district": "Merkez",
      "latitude": 41.4626387,
      "longitude": 31.8049076,
      "dutyStart": null,
      "dutyEnd": null,
      "lastVerifiedAt": "2026-04-14T06:47:01.392Z",
      "source": "e-Devlet / TİTCK",
      "sourceUrl": "https://www.turkiye.gov.tr/saglik-titck-nobetci-eczane-sorgulama"
    }
  ]
}
